jensen_mcp_demo/__init__.py
jensen_mcp_demo-0.1.1.dist-info/METADATA
jensen_mcp_demo-0.1.1.dist-info/WHEEL
jensen_mcp_demo-0.1.1.dist-info/entry_points.txt
jensen_mcp_demo-0.1.1.dist-info/RECORD
