Metadata-Version: 2.4
Name: jensen-mcp-demo
Version: 0.1.1
Summary: Add your description here
Author-email: "jensen.chen" <jensen.chen@klook.com>
Requires-Python: >=3.13
Requires-Dist: mcp[cli]>=1.13.1
